seleup/__init__.py
seleup-1.3.dist-info/METADATA
seleup-1.3.dist-info/WHEEL
seleup-1.3.dist-info/top_level.txt
seleup-1.3.dist-info/RECORD
