Metadata-Version: 2.1
Name: seleup
Version: 1.3
Summary: selenium automate update
Home-page: UNKNOWN
Author: complexplayer
Author-email: didutc@gmail.com
License: MIT
Platform: UNKNOWN
Requires-Python: >=3
